yaw/__init__.py
yaw/_version.py
yaw/binning.py
yaw/coordinates.py
yaw/cosmology.py
yaw/datachunk.py
yaw/options.py
yaw/randoms.py
yaw/redshifts.py
yaw/catalog/__init__.py
yaw/catalog/catalog.py
yaw/catalog/patch.py
yaw/catalog/readers.py
yaw/catalog/trees.py
yaw/cli/__init__.py
yaw/cli/commandline.py
yaw/cli/config.py
yaw/cli/directory.py
yaw/cli/handles.py
yaw/cli/logging.py
yaw/cli/pipeline.py
yaw/cli/plotting.py
yaw/cli/tasks.py
yaw/config/__init__.py
yaw/config/base.py
yaw/config/classes.py
yaw/correlation/__init__.py
yaw/correlation/corrdata.py
yaw/correlation/corrfunc.py
yaw/correlation/measurements.py
yaw/correlation/paircounts.py
yaw/examples/2dflens_kidss_data.pqt
yaw/examples/2dflens_kidss_rand_5x.pqt
yaw/examples/__init__.py
yaw/examples/auto.hdf
yaw/examples/cross.hdf
yaw/examples/estimate.cov
yaw/examples/estimate.dat
yaw/examples/estimate.smp
yaw/utils/__init__.py
yaw/utils/abc.py
yaw/utils/logging.py
yaw/utils/misc.py
yaw/utils/parallel.py
yaw/utils/plotting.py
yet_another_wizz-3.1.2.dist-info/licenses/LICENSE
yet_another_wizz-3.1.2.dist-info/METADATA
yet_another_wizz-3.1.2.dist-info/WHEEL
yet_another_wizz-3.1.2.dist-info/entry_points.txt
yet_another_wizz-3.1.2.dist-info/top_level.txt
yet_another_wizz-3.1.2.dist-info/RECORD
