Metadata-Version: 2.4
Name: yet_another_wizz
Version: 3.1.2
Summary: Implementation of the Schmidt et al. (2013) clustering redshift method.
Home-page: https://github.com/jlvdb/yet_another_wizz.git
Author-email: Jan Luca van den Busch <jlvdb@astro.ruhr-uni-bochum.de>
License: GPL-3.0-or-later
Classifier: Intended Audience :: Science/Research
Classifier: Topic :: Scientific/Engineering :: Astronomy
Classifier: Programming Language :: Python :: 3
Classifier: License :: OSI Approved :: GNU General Public License v3 or later (GPLv3+)
Requires-Python: >=3.10
License-File: LICENSE
Requires-Dist: astropy
Requires-Dist: deprecated
Requires-Dist: h5py
Requires-Dist: numpy
Requires-Dist: pyarrow
Requires-Dist: pyyaml
Requires-Dist: requests
Requires-Dist: scipy
Requires-Dist: StrEnum
Requires-Dist: treecorr>=4.3
Requires-Dist: typing-extensions
Provides-Extra: plot
Requires-Dist: matplotlib; extra == "plot"
Provides-Extra: mpi
Requires-Dist: mpi4py; extra == "mpi"
Provides-Extra: healpix
Requires-Dist: healpy; extra == "healpix"
Provides-Extra: docs
Requires-Dist: sphinx; extra == "docs"
Requires-Dist: sphinx-design; extra == "docs"
Requires-Dist: sphinx-copybutton; extra == "docs"
Requires-Dist: pydata-sphinx-theme; extra == "docs"
Provides-Extra: style
Requires-Dist: black; extra == "style"
Requires-Dist: isort; extra == "style"
Requires-Dist: flake8; extra == "style"
Requires-Dist: pre-commit; extra == "style"
Provides-Extra: test
Requires-Dist: yet_another_wizz[plot]; extra == "test"
Requires-Dist: yet_another_wizz[healpix]; extra == "test"
Requires-Dist: coverage; extra == "test"
Requires-Dist: pytest; extra == "test"
Requires-Dist: pytest-cov; extra == "test"
Requires-Dist: pytest-skip-slow; extra == "test"
Requires-Dist: pandas; extra == "test"
Provides-Extra: dev
Requires-Dist: yet_another_wizz[docs]; extra == "dev"
Requires-Dist: yet_another_wizz[test]; extra == "dev"
Requires-Dist: yet_another_wizz[style]; extra == "dev"
Requires-Dist: ipykernel; extra == "dev"
Dynamic: home-page
Dynamic: license-file
